dnnlib/__init__.py
dnnlib/util.py
jingan/__init__.py
jingan/jin_test.py
jingan/jin_util.py
jingan/res.py
jingan/session.py
metrics/__init__.py
metrics/frechet_inception_distance.py
metrics/inception_score.py
metrics/kernel_inception_distance.py
metrics/metric_main.py
metrics/metric_utils.py
metrics/perceptual_path_length.py
metrics/precision_recall.py
torch_utils/__init__.py
torch_utils/custom_ops.py
torch_utils/misc.py
torch_utils/persistence.py
torch_utils/training_stats.py
torch_utils/ops/__init__.py
torch_utils/ops/bias_act.py
torch_utils/ops/conv2d_gradfix.py
torch_utils/ops/conv2d_resample.py
torch_utils/ops/fma.py
torch_utils/ops/grid_sample_gradfix.py
torch_utils/ops/upfirdn2d.py
training/__init__.py
training/augment.py
training/dataset.py
training/loss.py
training/networks.py
training/training_loop.py
jingan-0.0.3.dist-info/LICENSE.txt
jingan-0.0.3.dist-info/METADATA
jingan-0.0.3.dist-info/WHEEL
jingan-0.0.3.dist-info/top_level.txt
jingan-0.0.3.dist-info/RECORD
