Metadata-Version: 2.1
Name: jingan
Version: 0.0.3
Summary: A small example package
Home-page: https://github.com/Seokhee-Jin/stylegan2-ada-pytorch
Author: not my work
Author-email: seokhee749@gmail.com
Classifier: Programming Language :: Python :: 3
Classifier: License :: OSI Approved :: MIT License
Classifier: Operating System :: OS Independent
Requires-Python: >=3.7
License-File: LICENSE.txt
